django_xlspopulator/__init__.py
django_xlspopulator/populator.py
django_xlspopulator-1.1.dist-info/LICENSE
django_xlspopulator-1.1.dist-info/METADATA
django_xlspopulator-1.1.dist-info/WHEEL
django_xlspopulator-1.1.dist-info/top_level.txt
django_xlspopulator-1.1.dist-info/RECORD
