Metadata-Version: 2.1
Name: django-xlspopulator
Version: 1.1
Summary: Populate your Django model from .xls file
Home-page: https://github.com/bloodwithmilk25/django-xlspopulator
Author: Nikita Tonkoshkur
Author-email: humapen@gmail.com
License: UNKNOWN
Platform: UNKNOWN
Classifier: Programming Language :: Python :: 3
Classifier: License :: OSI Approved :: MIT License
Classifier: Operating System :: OS Independent
